MANIFEST.in
Makefile
README.rst
README.txt
project.ini
requirements.txt
setup.py
aiohug_swagger/__init__.py
aiohug_swagger/decorators.py
aiohug_swagger/handlers.py
aiohug_swagger.egg-info/PKG-INFO
aiohug_swagger.egg-info/SOURCES.txt
aiohug_swagger.egg-info/dependency_links.txt
aiohug_swagger.egg-info/requires.txt
aiohug_swagger.egg-info/top_level.txt
aiohug_swagger/templates/redoc.html
aiohug_swagger/templates/swaggerui.html
aiohug_swagger/tests/__init__.py
aiohug_swagger/tests/application.py
aiohug_swagger/tests/test_decorators.py
aiohug_swagger/tests/test_handlers.py
aiohug_swagger/tests/test_swagger_generator.py