Metadata-Version: 1.0
Name: aiohug-swagger
Version: 0.1
Summary: aiohug_swagger
Home-page: https://github.com/nonamenix/aiohug_swagger
Author: nonamenix
Author-email: nonamenix@gmail.com
License: UNKNOWN
Platform: UNKNOWN
